Metadata-Version: 2.1
Name: grython
Version: 0.0.0
Summary: Light weight python crawler framework
Home-page: UNKNOWN
Author: Queenferry
Author-email: queensferry.me@gmail.com
License: UNKNOWN
Platform: UNKNOWN
Classifier: Programming Language :: Python :: 3
Classifier: License :: OSI Approved :: MIT License
Classifier: Operating System :: OS Independent
